<?xml version="1.0" encoding="UTF-8"?>
<root>
  <language id="english">
    <entry id="menu_base_element_return_to_game"><![CDATA[Revenir en Jeu]]></entry>
    <entry id="" />
    <entry id="" />
    <entry id="menu_controls_category_0"><![CDATA[GENERAL]]></entry>
    <entry id="menu_controls_element_0_0"><![CDATA[H - Aides contextuelle pour tous les écrans]]></entry>
    <entry id="menu_controls_category_1"><![CDATA[Raid]]></entry>
    <entry id="menu_controls_element_1_0"><![CDATA[A - Déplacer à Droite]]></entry>
    <entry id="menu_controls_element_1_1"><![CDATA[D - Déplacer à Gauche]]></entry>
    <entry id="menu_controls_category_2"><![CDATA[Ville]]></entry>
    <entry id="menu_controls_element_2_0"><![CDATA[Glisser-Déposer]]></entry>
    <entry id="" />
    <entry id="" />
    <entry id="menu_options_require_restart"><![CDATA[Vous devrez redémarrer le jeu pour que ces changements soient appliqués.]]></entry>
    <entry id="" />
    <entry id="" />
    <entry id="menu_options_value_seperation_resolution"><![CDATA[x]]></entry>
    <entry id="" />
    <entry id="menu_options_back_confirm_dialog_question"><![CDATA[Enregistrer ces changements?]]></entry>
    <entry id="menu_options_back_confirm_dialog_answer_save"><![CDATA[ENREGISTRER]]></entry>
    <entry id="menu_options_back_confirm_dialog_answer_discard"><![CDATA[JETER]]></entry>
    <entry id="" />
    <entry id="" />
    <entry id="OPTIONS SCREEN" />
    <entry id="menu_options_element_fullscreen"><![CDATA[Plein ecran?]]></entry>
    <entry id="menu_options_element_monitor_number"><![CDATA[Numéro Moniteur]]></entry>
    <entry id="menu_options_element_resolution"><![CDATA[Résolution]]></entry>
    <entry id="menu_options_element_sfx_volume"><![CDATA[Volume SFX]]></entry>
    <entry id="menu_options_element_music_volume"><![CDATA[Volume Musique]]></entry>
    <entry id="menu_options_element_narration_volume"><![CDATA[Volume Narration]]></entry>
    <entry id="menu_options_element_video_volume"><![CDATA[Volume Cinématiques]]></entry>
    <entry id="menu_options_element_metrics"><![CDATA[Autoriser la collecte anonyme de données]]></entry>
    <entry id="menu_options_element_combat_pivot_camera"><![CDATA[Caméra Pivot de Combat]]></entry>
    <entry id="menu_options_element_extra_bark_time"><![CDATA[Temps supplémentaire d'embarquement (secondes)]]></entry>
    <entry id="" />
    <entry id="menu_base_element_view_options"><![CDATA[Options]]></entry>
    <entry id="menu_base_element_view_controls"><![CDATA[Contrôles]]></entry>
    <entry id="menu_base_element_watch_intro"><![CDATA[Regarder la Cinématique d'Introduction]]></entry>
    <entry id="menu_base_element_exit_campaign"><![CDATA[Quitter vers le Menu Principal]]></entry>
    <entry id="menu_base_element_exit_game"><![CDATA[Quitter vers le Bureau]]></entry>
  </language>
  <language id="french">
    <entry id="menu_base_element_return_to_game" />
    <entry id="" />
    <entry id="" />
    <entry id="menu_controls_category_0" />
    <entry id="menu_controls_element_0_0" />
    <entry id="menu_controls_category_1" />
    <entry id="menu_controls_element_1_0" />
    <entry id="menu_controls_element_1_1" />
    <entry id="menu_controls_category_2" />
    <entry id="menu_controls_element_2_0" />
    <entry id="" />
    <entry id="" />
    <entry id="menu_options_require_restart" />
    <entry id="" />
    <entry id="" />
    <entry id="menu_options_value_seperation_resolution" />
    <entry id="" />
    <entry id="menu_options_back_confirm_dialog_question" />
    <entry id="menu_options_back_confirm_dialog_answer_save" />
    <entry id="menu_options_back_confirm_dialog_answer_discard" />
    <entry id="" />
    <entry id="" />
    <entry id="OPTIONS SCREEN" />
    <entry id="menu_options_element_fullscreen" />
    <entry id="menu_options_element_monitor_number" />
    <entry id="menu_options_element_resolution" />
    <entry id="menu_options_element_sfx_volume" />
    <entry id="menu_options_element_music_volume" />
    <entry id="menu_options_element_narration_volume" />
    <entry id="menu_options_element_video_volume" />
    <entry id="menu_options_element_metrics" />
    <entry id="menu_options_element_combat_pivot_camera" />
    <entry id="menu_options_element_extra_bark_time" />
    <entry id="" />
    <entry id="menu_base_element_view_options" />
    <entry id="menu_base_element_view_controls" />
    <entry id="menu_base_element_watch_intro" />
    <entry id="menu_base_element_exit_campaign" />
    <entry id="menu_base_element_exit_game" />
  </language>
  <language id="italian">
    <entry id="menu_base_element_return_to_game" />
    <entry id="" />
    <entry id="" />
    <entry id="menu_controls_category_0" />
    <entry id="menu_controls_element_0_0" />
    <entry id="menu_controls_category_1" />
    <entry id="menu_controls_element_1_0" />
    <entry id="menu_controls_element_1_1" />
    <entry id="menu_controls_category_2" />
    <entry id="menu_controls_element_2_0" />
    <entry id="" />
    <entry id="" />
    <entry id="menu_options_require_restart" />
    <entry id="" />
    <entry id="" />
    <entry id="menu_options_value_seperation_resolution" />
    <entry id="" />
    <entry id="menu_options_back_confirm_dialog_question" />
    <entry id="menu_options_back_confirm_dialog_answer_save" />
    <entry id="menu_options_back_confirm_dialog_answer_discard" />
    <entry id="" />
    <entry id="" />
    <entry id="OPTIONS SCREEN" />
    <entry id="menu_options_element_fullscreen" />
    <entry id="menu_options_element_monitor_number" />
    <entry id="menu_options_element_resolution" />
    <entry id="menu_options_element_sfx_volume" />
    <entry id="menu_options_element_music_volume" />
    <entry id="menu_options_element_narration_volume" />
    <entry id="menu_options_element_video_volume" />
    <entry id="menu_options_element_metrics" />
    <entry id="menu_options_element_combat_pivot_camera" />
    <entry id="menu_options_element_extra_bark_time" />
    <entry id="" />
    <entry id="menu_base_element_view_options" />
    <entry id="menu_base_element_view_controls" />
    <entry id="menu_base_element_watch_intro" />
    <entry id="menu_base_element_exit_campaign" />
    <entry id="menu_base_element_exit_game" />
  </language>
  <language id="german">
    <entry id="menu_base_element_return_to_game" />
    <entry id="" />
    <entry id="" />
    <entry id="menu_controls_category_0" />
    <entry id="menu_controls_element_0_0" />
    <entry id="menu_controls_category_1" />
    <entry id="menu_controls_element_1_0" />
    <entry id="menu_controls_element_1_1" />
    <entry id="menu_controls_category_2" />
    <entry id="menu_controls_element_2_0" />
    <entry id="" />
    <entry id="" />
    <entry id="menu_options_require_restart" />
    <entry id="" />
    <entry id="" />
    <entry id="menu_options_value_seperation_resolution" />
    <entry id="" />
    <entry id="menu_options_back_confirm_dialog_question" />
    <entry id="menu_options_back_confirm_dialog_answer_save" />
    <entry id="menu_options_back_confirm_dialog_answer_discard" />
    <entry id="" />
    <entry id="" />
    <entry id="OPTIONS SCREEN" />
    <entry id="menu_options_element_fullscreen" />
    <entry id="menu_options_element_monitor_number" />
    <entry id="menu_options_element_resolution" />
    <entry id="menu_options_element_sfx_volume" />
    <entry id="menu_options_element_music_volume" />
    <entry id="menu_options_element_narration_volume" />
    <entry id="menu_options_element_video_volume" />
    <entry id="menu_options_element_metrics" />
    <entry id="menu_options_element_combat_pivot_camera" />
    <entry id="menu_options_element_extra_bark_time" />
    <entry id="" />
    <entry id="menu_base_element_view_options" />
    <entry id="menu_base_element_view_controls" />
    <entry id="menu_base_element_watch_intro" />
    <entry id="menu_base_element_exit_campaign" />
    <entry id="menu_base_element_exit_game" />
  </language>
  <language id="spanish">
    <entry id="menu_base_element_return_to_game" />
    <entry id="" />
    <entry id="" />
    <entry id="menu_controls_category_0" />
    <entry id="menu_controls_element_0_0" />
    <entry id="menu_controls_category_1" />
    <entry id="menu_controls_element_1_0" />
    <entry id="menu_controls_element_1_1" />
    <entry id="menu_controls_category_2" />
    <entry id="menu_controls_element_2_0" />
    <entry id="" />
    <entry id="" />
    <entry id="menu_options_require_restart" />
    <entry id="" />
    <entry id="" />
    <entry id="menu_options_value_seperation_resolution" />
    <entry id="" />
    <entry id="menu_options_back_confirm_dialog_question" />
    <entry id="menu_options_back_confirm_dialog_answer_save" />
    <entry id="menu_options_back_confirm_dialog_answer_discard" />
    <entry id="" />
    <entry id="" />
    <entry id="OPTIONS SCREEN" />
    <entry id="menu_options_element_fullscreen" />
    <entry id="menu_options_element_monitor_number" />
    <entry id="menu_options_element_resolution" />
    <entry id="menu_options_element_sfx_volume" />
    <entry id="menu_options_element_music_volume" />
    <entry id="menu_options_element_narration_volume" />
    <entry id="menu_options_element_video_volume" />
    <entry id="menu_options_element_metrics" />
    <entry id="menu_options_element_combat_pivot_camera" />
    <entry id="menu_options_element_extra_bark_time" />
    <entry id="" />
    <entry id="menu_base_element_view_options" />
    <entry id="menu_base_element_view_controls" />
    <entry id="menu_base_element_watch_intro" />
    <entry id="menu_base_element_exit_campaign" />
    <entry id="menu_base_element_exit_game" />
  </language>
</root>

